<?xml version="1.0" encoding="UTF-8"?>
<episodeCollections datalog="../Datalog/generic_optimization.datalog">
  <episodeCollection name="rule13_update1_op1">
    <episode timestamp="1289415657361">
      <trialInfo order="[m2, [now1, this1, this2], [nowCtxt1, thisCtxt1], m1, [now2, nowCtxt2], thisCtxt2]" cost="234" timestamp="1289415659347" varLowerBound="-1.0" varUpperBound="-1.0" attrLowerBound="-1.0" attrUpperBound="-1.0" domLowerBound="-1.0" domUpperBound="-1.0" />
      <trialInfo order="[now2, [m2, nowCtxt2, this1, thisCtxt2], [m1, nowCtxt1], now1, [this2, thisCtxt1]]" cost="813" timestamp="1289415661002" varLowerBound="-1.0" varUpperBound="-1.0" attrLowerBound="-1.0" attrUpperBound="-1.0" domLowerBound="0.0" domUpperBound="1.7976931348623157E308" />
      <trialInfo order="[[this2, thisCtxt2], [now1, nowCtxt1, this1, thisCtxt1], now2, nowCtxt2, [m1, m2]]" cost="257" timestamp="1289415662035" varLowerBound="0.0" varUpperBound="1.7976931348623157E308" attrLowerBound="0.0" attrUpperBound="1.7976931348623157E308" domLowerBound="0.0" domUpperBound="1.7976931348623157E308" />
      <trialInfo order="[[m1, m2, now1, now2, this1, this2, thisCtxt1], [nowCtxt1, nowCtxt2, thisCtxt2]]" cost="3865" timestamp="1289415666613" varLowerBound="0.0" varUpperBound="1.7976931348623157E308" attrLowerBound="0.0" attrUpperBound="1.7976931348623157E308" domLowerBound="0.0" domUpperBound="1.7976931348623157E308" />
      <trialInfo order="[[m1, nowCtxt1, nowCtxt2, this1, thisCtxt1, thisCtxt2], [m2, now1, now2], this2]" cost="412" timestamp="1289415668047" varLowerBound="2.280851063829787" varUpperBound="1.7976931348623157E308" attrLowerBound="0.0" attrUpperBound="1.7976931348623157E308" domLowerBound="0.0" domUpperBound="1.7976931348623157E308" />
      <trialInfo order="[m2, [this1, thisCtxt2], this2, [m1, nowCtxt1], nowCtxt2, [now1, now2, thisCtxt1]]" cost="107" timestamp="1289415668820" varLowerBound="0.0" varUpperBound="2.6106382978723404" attrLowerBound="0.0" attrUpperBound="1.7976931348623157E308" domLowerBound="0.0" domUpperBound="1.7976931348623157E308" />
      <trialInfo order="[now1, this2, m1, [m2, thisCtxt1], this1, nowCtxt2, [now2, nowCtxt1, thisCtxt2]]" cost="262" timestamp="1289415669645" varLowerBound="0.0" varUpperBound="1.4276595744680851" attrLowerBound="0.0" attrUpperBound="1.7976931348623157E308" domLowerBound="0.0" domUpperBound="1.7976931348623157E308" />
      <trialInfo order="[m2, [now2, nowCtxt1, nowCtxt2, thisCtxt1], m1, [now1, this1], this2, thisCtxt2]" cost="92" timestamp="1289415670336" varLowerBound="2.0963159968479115" varUpperBound="1.7976931348623157E308" attrLowerBound="0.0" attrUpperBound="1.7976931348623157E308" domLowerBound="0.0" domUpperBound="1.7976931348623157E308" />
      <trialInfo order="[[m1, m2, now1, nowCtxt1, nowCtxt2, this1, this2], now2, [thisCtxt1, thisCtxt2]]" cost="2479" timestamp="1289415673464" varLowerBound="1.4276595744680851" varUpperBound="1.7976931348623157E308" attrLowerBound="0.0" attrUpperBound="1.7976931348623157E308" domLowerBound="0.0" domUpperBound="1.7976931348623157E308" />
      <trialInfo order="[nowCtxt1, [m2, thisCtxt2], [this1, this2], now2, now1, [nowCtxt2, thisCtxt1], m1]" cost="50" timestamp="1289415674273" varLowerBound="0.0" varUpperBound="1.048936170212766" attrLowerBound="0.0" attrUpperBound="1.7976931348623157E308" domLowerBound="0.0" domUpperBound="1.7976931348623157E308" />
      <trialInfo order="[nowCtxt1, [m1, m2, thisCtxt1], [now1, now2, nowCtxt2, this1, this2, thisCtxt2]]" cost="852" timestamp="1289415675749" varLowerBound="-1.0" varUpperBound="-1.0" attrLowerBound="0.0" attrUpperBound="1.7976931348623157E308" domLowerBound="0.0" domUpperBound="1.7976931348623157E308" />
      <trialInfo order="[[now1, now2, nowCtxt2, this1, thisCtxt1, thisCtxt2], this2, m2, [m1, nowCtxt1]]" cost="125" timestamp="1289415676592" varLowerBound="-1.0" varUpperBound="-1.0" attrLowerBound="0.0" attrUpperBound="1.7976931348623157E308" domLowerBound="0.0" domUpperBound="1.7976931348623157E308" />
      <trialInfo order="[[m2, this1, this2, thisCtxt1, thisCtxt2], [m1, now1, now2, nowCtxt1, nowCtxt2]]" cost="793" timestamp="1289415678220" varLowerBound="2.96720901126408" varUpperBound="1.7976931348623157E308" attrLowerBound="0.0" attrUpperBound="1.7976931348623157E308" domLowerBound="0.0" domUpperBound="1.7976931348623157E308" />
      <trialInfo order="[now2, this1, [m2, now1, nowCtxt1], [m1, nowCtxt2, this2, thisCtxt1], thisCtxt2]" cost="537" timestamp="1289415679451" varLowerBound="0.0" varUpperBound="1.048936170212766" attrLowerBound="0.0" attrUpperBound="1.7976931348623157E308" domLowerBound="0.0" domUpperBound="1.7976931348623157E308" />
      <trialInfo order="[[nowCtxt1, thisCtxt2], [nowCtxt2, thisCtxt1], [m1, now2], [m2, now1, this1, this2]]" cost="172" timestamp="1289415680251" varLowerBound="-1.0" varUpperBound="-1.0" attrLowerBound="0.0" attrUpperBound="1.7976931348623157E308" domLowerBound="0.0" domUpperBound="1.7976931348623157E308" />
      <trialInfo order="[[m2, nowCtxt1, this1], [m1, nowCtxt2], this2, thisCtxt2, [now2, thisCtxt1], now1]" cost="326" timestamp="1289415681210" varLowerBound="0.0" varUpperBound="1.4276595744680851" attrLowerBound="0.0" attrUpperBound="1.7976931348623157E308" domLowerBound="0.0" domUpperBound="1.7976931348623157E308" />
      <trialInfo order="[m2, nowCtxt2, nowCtxt1, thisCtxt2, [m1, this2], this1, thisCtxt1, [now1, now2]]" cost="31" timestamp="1289415681747" varLowerBound="0.0" varUpperBound="1.048936170212766" attrLowerBound="0.0" attrUpperBound="2.931372549019608" domLowerBound="0.0" domUpperBound="1.7976931348623157E308" />
      <trialInfo order="[[m2, nowCtxt1], this1, [m1, now1, now2, nowCtxt2, this2, thisCtxt1, thisCtxt2]]" cost="4014" timestamp="1289415686319" varLowerBound="0.0" varUpperBound="1.048936170212766" attrLowerBound="0.0" attrUpperBound="2.931372549019608" domLowerBound="0.0" domUpperBound="1.7976931348623157E308" />
      <trialInfo order="[[m2, nowCtxt1], m1, [nowCtxt2, thisCtxt1], [now1, now2, this1, this2, thisCtxt2]]" cost="466" timestamp="1289415687405" varLowerBound="0.0" varUpperBound="1.048936170212766" attrLowerBound="0.0" attrUpperBound="2.931372549019608" domLowerBound="0.0" domUpperBound="1.7976931348623157E308" />
      <trialInfo order="[nowCtxt2, m2, [this2, thisCtxt2], [m1, now1, now2, nowCtxt1, this1, thisCtxt1]]" cost="16" timestamp="1289415688054" varLowerBound="3.42799332498957" varUpperBound="16.009845640383812" attrLowerBound="0.0" attrUpperBound="3.42799332498957" domLowerBound="0.0" domUpperBound="1.7976931348623157E308" />
      <trialInfo order="[m2, m1, [now1, this2], this1, [nowCtxt1, thisCtxt1, thisCtxt2], nowCtxt2, now2]" cost="284" timestamp="1289415689089" varLowerBound="0.0" varUpperBound="1.048936170212766" attrLowerBound="0.0" attrUpperBound="2.931372549019608" domLowerBound="0.0" domUpperBound="1.7976931348623157E308" />
      <trialInfo order="[m2, [now2, nowCtxt1, this2, thisCtxt1], m1, thisCtxt2, this1, [now1, nowCtxt2]]" cost="129" timestamp="1289415689885" varLowerBound="0.0" varUpperBound="1.048936170212766" attrLowerBound="0.0" attrUpperBound="3.42799332498957" domLowerBound="0.0" domUpperBound="1.7976931348623157E308" />
      <trialInfo order="[[m1, this2], m2, [now2, nowCtxt2, this1], [nowCtxt1, thisCtxt1], thisCtxt2, now1]" cost="196" timestamp="1289415690694" varLowerBound="0.0" varUpperBound="1.048936170212766" attrLowerBound="-1.0" attrUpperBound="-1.0" domLowerBound="0.0" domUpperBound="1.7976931348623157E308" />
      <trialInfo order="[m2, [this2, thisCtxt1], [m1, now1, now2, nowCtxt1], nowCtxt2, [this1, thisCtxt2]]" cost="264" timestamp="1289415691540" varLowerBound="-1.0" varUpperBound="-1.0" attrLowerBound="-1.0" attrUpperBound="-1.0" domLowerBound="0.0" domUpperBound="1.7976931348623157E308" />
      <trialInfo order="[[m2, thisCtxt2], [nowCtxt1, this1, thisCtxt1], [m1, now1, now2, this2], nowCtxt2]" cost="468" timestamp="1289415692614" varLowerBound="-1.0" varUpperBound="-1.0" attrLowerBound="-1.0" attrUpperBound="-1.0" domLowerBound="0.0" domUpperBound="1.7976931348623157E308" />
      <trialInfo order="[m2, [now2, thisCtxt1, thisCtxt2], [nowCtxt2, this2], m1, this1, nowCtxt1, now1]" cost="74" timestamp="1289415693327" varLowerBound="-1.0" varUpperBound="-1.0" attrLowerBound="0.0" attrUpperBound="7.029411764705882" domLowerBound="0.0" domUpperBound="1.7976931348623157E308" />
      <trialInfo order="[thisCtxt2, m2, [m1, nowCtxt1, this1], [nowCtxt2, this2], [now1, thisCtxt1], now2]" cost="582" timestamp="1289415694571" varLowerBound="-1.0" varUpperBound="-1.0" attrLowerBound="0.0" attrUpperBound="5.411764705882353" domLowerBound="0.0" domUpperBound="1.7976931348623157E308" />
      <trialInfo order="[thisCtxt2, now1, m2, [m1, this1, this2], [now2, nowCtxt2], [nowCtxt1, thisCtxt1]]" cost="135" timestamp="1289415695253" varLowerBound="-1.0" varUpperBound="-1.0" attrLowerBound="0.0" attrUpperBound="7.029411764705882" domLowerBound="0.0" domUpperBound="1.7976931348623157E308" />
      <trialInfo order="[m2, this2, [m1, nowCtxt1, nowCtxt2], thisCtxt1, now2, [now1, this1, thisCtxt2]]" cost="128" timestamp="1289415696015" varLowerBound="0.0" varUpperBound="1.048936170212766" attrLowerBound="0.0" attrUpperBound="7.029411764705882" domLowerBound="0.0" domUpperBound="1.7976931348623157E308" />
      <trialInfo order="[[now2, thisCtxt2], m2, [m1, nowCtxt2], [nowCtxt1, this2], thisCtxt1, [now1, this1]]" cost="85" timestamp="1289415696712" varLowerBound="-1.0" varUpperBound="-1.0" attrLowerBound="0.0" attrUpperBound="7.617647058823529" domLowerBound="0.0" domUpperBound="1.7976931348623157E308" />
      <trialInfo order="[[m2, nowCtxt1, this2], [m1, now1, now2, nowCtxt2, this1, thisCtxt1, thisCtxt2]]" cost="557" timestamp="1289415698028" varLowerBound="9.274509803921568" varUpperBound="16.588277012932835" attrLowerBound="7.0" attrUpperBound="1.7976931348623157E308" domLowerBound="0.0" domUpperBound="1.7976931348623157E308" />
      <trialInfo order="[m2, [now1, nowCtxt1, this2, thisCtxt1], [this1, thisCtxt2], now2, nowCtxt2, m1]" cost="233" timestamp="1289415698878" varLowerBound="-1.0" varUpperBound="-1.0" attrLowerBound="0.0" attrUpperBound="7.617647058823529" domLowerBound="0.0" domUpperBound="1.7976931348623157E308" />
      <trialInfo order="[this2, this1, thisCtxt1, [m1, m2, nowCtxt1], nowCtxt2, thisCtxt2, now2, now1]" cost="324" timestamp="1289415699775" varLowerBound="-1.0" varUpperBound="-1.0" attrLowerBound="-1.0" attrUpperBound="-1.0" domLowerBound="0.0" domUpperBound="1.7976931348623157E308" />
      <trialInfo order="[this2, m2, [now1, now2, thisCtxt2], [m1, nowCtxt1, nowCtxt2], this1, thisCtxt1]" cost="4" timestamp="1289415700407" varLowerBound="5.735294117647059" varUpperBound="12.676470588235293" attrLowerBound="-1.0" attrUpperBound="-1.0" domLowerBound="0.0" domUpperBound="1.7976931348623157E308" />
      <trialInfo order="[nowCtxt2, [m1, now1], [m2, now2, nowCtxt1, this2, thisCtxt1], thisCtxt2, this1]" cost="593" timestamp="1289415701601" varLowerBound="1.048936170212766" varUpperBound="4.735294117647059" attrLowerBound="7.617647058823529" attrUpperBound="1.7976931348623157E308" domLowerBound="0.0" domUpperBound="1.7976931348623157E308" />
      <trialInfo order="[nowCtxt2, [m2, now2, nowCtxt1], this1, [m1, now1, thisCtxt2], thisCtxt1, this2]" cost="219" timestamp="1289415702409" varLowerBound="-1.0" varUpperBound="-1.0" attrLowerBound="0.0" attrUpperBound="7.8235294117647065" domLowerBound="0.0" domUpperBound="1.7976931348623157E308" />
      <trialInfo order="[m2, now2, [m1, now1, nowCtxt1, nowCtxt2, thisCtxt2], [this1, this2], thisCtxt1]" cost="192" timestamp="1289415703186" varLowerBound="1.048936170212766" varUpperBound="3.9377972465581976" attrLowerBound="7.8235294117647065" attrUpperBound="1.7976931348623157E308" domLowerBound="0.0" domUpperBound="1.7976931348623157E308" />
      <trialInfo order="[[m2, thisCtxt2], nowCtxt1, [m1, nowCtxt2], [now1, this1], [this2, thisCtxt1], now2]" cost="331" timestamp="1289415704142" varLowerBound="-1.0" varUpperBound="-1.0" attrLowerBound="0.0" attrUpperBound="9.274509803921568" domLowerBound="0.0" domUpperBound="1.7976931348623157E308" />
      <trialInfo order="[[m1, this2, thisCtxt2], this1, nowCtxt2, nowCtxt1, [m2, now1, now2, thisCtxt1]]" cost="217" timestamp="1289415704974" varLowerBound="33.55882352941177" varUpperBound="1.7976931348623157E308" attrLowerBound="0.0" attrUpperBound="9.274509803921568" domLowerBound="0.0" domUpperBound="1.7976931348623157E308" />
      <trialInfo order="[nowCtxt2, m1, m2, this1, [now1, now2, nowCtxt1, this2, thisCtxt1, thisCtxt2]]" cost="317" timestamp="1289415705930" varLowerBound="-1.0" varUpperBound="-1.0" attrLowerBound="11.068627450980392" attrUpperBound="1.7976931348623157E308" domLowerBound="0.0" domUpperBound="1.7976931348623157E308" />
      <trialInfo order="[[m2, this2], nowCtxt2, nowCtxt1, m1, [now1, now2], thisCtxt2, this1, thisCtxt1]" cost="47" timestamp="1289415706652" varLowerBound="-1.0" varUpperBound="-1.0" attrLowerBound="0.0" attrUpperBound="11.068627450980392" domLowerBound="0.0" domUpperBound="1.7976931348623157E308" />
      <trialInfo order="[this2, thisCtxt2, [m1, m2, nowCtxt2], [now1, now2, nowCtxt1, this1, thisCtxt1]]" cost="72" timestamp="1289415707303" varLowerBound="-1.0" varUpperBound="-1.0" attrLowerBound="11.068627450980392" attrUpperBound="1.7976931348623157E308" domLowerBound="0.0" domUpperBound="1.7976931348623157E308" />
      <trialInfo order="[nowCtxt2, [this2, thisCtxt2], [m1, m2, nowCtxt1], [now1, now2, thisCtxt1], this1]" cost="56" timestamp="1289415707911" varLowerBound="-1.0" varUpperBound="-1.0" attrLowerBound="0.0" attrUpperBound="11.068627450980392" domLowerBound="0.0" domUpperBound="1.7976931348623157E308" />
      <trialInfo order="[nowCtxt2, m2, this2, thisCtxt1, [m1, now1, now2, thisCtxt2], [nowCtxt1, this1]]" cost="153" timestamp="1289415708700" varLowerBound="-1.0" varUpperBound="-1.0" attrLowerBound="11.494117647058824" attrUpperBound="1.7976931348623157E308" domLowerBound="0.0" domUpperBound="1.7976931348623157E308" />
      <trialInfo order="[[nowCtxt1, nowCtxt2, thisCtxt2], this2, m1, [m2, this1], now2, [now1, thisCtxt1]]" cost="121" timestamp="1289415709437" varLowerBound="-1.0" varUpperBound="-1.0" attrLowerBound="0.0" attrUpperBound="11.494117647058824" domLowerBound="0.0" domUpperBound="1.7976931348623157E308" />
      <trialInfo order="[nowCtxt1, [nowCtxt2, this1], [m1, m2, now2, thisCtxt2], this2, [now1, thisCtxt1]]" cost="798" timestamp="1289415710851" varLowerBound="-1.0" varUpperBound="-1.0" attrLowerBound="0.0" attrUpperBound="12.676470588235293" domLowerBound="0.0" domUpperBound="1.7976931348623157E308" />
      <trialInfo order="[nowCtxt2, thisCtxt1, m2, [m1, now2, nowCtxt1, this1, this2], [now1, thisCtxt2]]" cost="366" timestamp="1289415711840" varLowerBound="14.179227941176471" varUpperBound="17.941176470588236" attrLowerBound="12.676470588235293" attrUpperBound="1.7976931348623157E308" domLowerBound="0.0" domUpperBound="1.7976931348623157E308" />
      <trialInfo order="[[m2, nowCtxt2], [m1, nowCtxt1, this2, thisCtxt2], [now1, now2, this1, thisCtxt1]]" cost="157" timestamp="1289415712613" varLowerBound="-1.0" varUpperBound="-1.0" attrLowerBound="14.179227941176471" attrUpperBound="1.7976931348623157E308" domLowerBound="0.0" domUpperBound="1.7976931348623157E308" />
      <trialInfo order="[[m1, now2, nowCtxt1, this1, this2], thisCtxt2, [now1, nowCtxt2], m2, thisCtxt1]" cost="210" timestamp="1289415713598" varLowerBound="41.1" varUpperBound="1.7976931348623157E308" attrLowerBound="0.0" attrUpperBound="14.179227941176471" domLowerBound="0.0" domUpperBound="1.7976931348623157E308" />
      <trialInfo order="[[now2, nowCtxt1, nowCtxt2], [m1, this2], [m2, now1, thisCtxt1], thisCtxt2, this1]" cost="212" timestamp="1289415714418" varLowerBound="-1.0" varUpperBound="-1.0" attrLowerBound="0.0" attrUpperBound="14.596875" domLowerBound="0.0" domUpperBound="1.7976931348623157E308" />
      <trialInfo order="[this1, now2, now1, m2, thisCtxt1, [nowCtxt1, this2], nowCtxt2, m1, thisCtxt2]" cost="84" timestamp="1289415715128" varLowerBound="-1.0" varUpperBound="-1.0" attrLowerBound="0.0" attrUpperBound="14.596875" domLowerBound="0.0" domUpperBound="1.7976931348623157E308" />
      <trialInfo order="[[m2, this1], [now1, thisCtxt1], [m1, nowCtxt1, this2, thisCtxt2], now2, nowCtxt2]" cost="733" timestamp="1289415716460" varLowerBound="-1.0" varUpperBound="-1.0" attrLowerBound="-1.0" attrUpperBound="-1.0" domLowerBound="0.0" domUpperBound="1.7976931348623157E308" />
      <trialInfo order="[[now2, nowCtxt1, this1, thisCtxt1], m1, m2, [now1, nowCtxt2, this2, thisCtxt2]]" cost="6" timestamp="1289415717080" varLowerBound="11.494117647058824" varUpperBound="16.745098039215687" attrLowerBound="-1.0" attrUpperBound="-1.0" domLowerBound="0.0" domUpperBound="1.7976931348623157E308" />
      <trialInfo order="[[m2, nowCtxt1, nowCtxt2], thisCtxt2, now2, m1, [this1, this2], [now1, thisCtxt1]]" cost="45" timestamp="1289415717768" varLowerBound="-1.0" varUpperBound="-1.0" attrLowerBound="0.0" attrUpperBound="15.084313725490196" domLowerBound="0.0" domUpperBound="1.7976931348623157E308" />
      <trialInfo order="[this2, thisCtxt2, now2, [nowCtxt1, this1], [m1, m2], [now1, nowCtxt2, thisCtxt1]]" cost="124" timestamp="1289415718589" varLowerBound="-1.0" varUpperBound="-1.0" attrLowerBound="0.0" attrUpperBound="14.596875" domLowerBound="0.0" domUpperBound="1.7976931348623157E308" />
      <trialInfo order="[this2, [m1, m2, nowCtxt1, thisCtxt2], [now1, this1, thisCtxt1], nowCtxt2, now2]" cost="499" timestamp="1289415719759" varLowerBound="-1.0" varUpperBound="-1.0" attrLowerBound="0.0" attrUpperBound="15.084313725490196" domLowerBound="0.0" domUpperBound="1.7976931348623157E308" />
      <trialInfo order="[m2, this1, [nowCtxt1, nowCtxt2], thisCtxt2, [m1, this2], [now1, thisCtxt1], now2]" cost="465" timestamp="1289415720872" varLowerBound="0.0" varUpperBound="1.248936170212766" attrLowerBound="-1.0" attrUpperBound="-1.0" domLowerBound="0.0" domUpperBound="1.7976931348623157E308" />
      <trialInfo order="[[this1, this2], now1, m2, [m1, nowCtxt1, thisCtxt1], [now2, nowCtxt2, thisCtxt2]]" cost="386" timestamp="1289415721893" varLowerBound="-1.0" varUpperBound="-1.0" attrLowerBound="-1.0" attrUpperBound="-1.0" domLowerBound="0.0" domUpperBound="1.7976931348623157E308" />
      <trialInfo order="[m2, [now2, nowCtxt1, thisCtxt1], [m1, now1, nowCtxt2, this1, this2], thisCtxt2]" cost="430" timestamp="1289415722976" varLowerBound="-1.0" varUpperBound="-1.0" attrLowerBound="-1.0" attrUpperBound="-1.0" domLowerBound="0.0" domUpperBound="1.7976931348623157E308" />
      <trialInfo order="[[m1, this1], [m2, nowCtxt1], [now1, now2, nowCtxt2, thisCtxt2], [this2, thisCtxt1]]" cost="257" timestamp="1289415724024" varLowerBound="-1.0" varUpperBound="-1.0" attrLowerBound="0.0" attrUpperBound="16.01964956195244" domLowerBound="0.0" domUpperBound="1.7976931348623157E308" />
      <trialInfo order="[[m2, nowCtxt1, nowCtxt2], [now2, this2], now1, m1, this1, thisCtxt2, thisCtxt1]" cost="25" timestamp="1289415724722" varLowerBound="-1.0" varUpperBound="-1.0" attrLowerBound="-1.0" attrUpperBound="-1.0" domLowerBound="0.0" domUpperBound="1.7976931348623157E308" />
      <trialInfo order="[[now1, this1, this2], m1, [nowCtxt1, thisCtxt1], [m2, now2, nowCtxt2, thisCtxt2]]" cost="162" timestamp="1289415725589" varLowerBound="-1.0" varUpperBound="-1.0" attrLowerBound="-1.0" attrUpperBound="-1.0" domLowerBound="0.0" domUpperBound="1.7976931348623157E308" />
      <trialInfo order="[[m1, m2, nowCtxt1], this2, [now1, this1, thisCtxt2], now2, [nowCtxt2, thisCtxt1]]" cost="361" timestamp="1289415726591" varLowerBound="-1.0" varUpperBound="-1.0" attrLowerBound="-1.0" attrUpperBound="-1.0" domLowerBound="0.0" domUpperBound="1.7976931348623157E308" />
      <trialInfo order="[m2, m1, thisCtxt2, [now1, now2, nowCtxt1, nowCtxt2, thisCtxt1], this2, this1]" cost="573" timestamp="1289415727778" varLowerBound="21.758823529411764" varUpperBound="36.44705882352942" attrLowerBound="0.0" attrUpperBound="16.588277012932835" domLowerBound="0.0" domUpperBound="1.7976931348623157E308" />
      <trialInfo order="[[now1, this2], m1, [m2, nowCtxt1], [now2, thisCtxt2], nowCtxt2, thisCtxt1, this1]" cost="264" timestamp="1289415728672" varLowerBound="-1.0" varUpperBound="-1.0" attrLowerBound="-1.0" attrUpperBound="-1.0" domLowerBound="0.0" domUpperBound="1.7976931348623157E308" />
      <trialInfo order="[m2, [m1, nowCtxt1], now1, [now2, nowCtxt2, this1, this2, thisCtxt1, thisCtxt2]]" cost="1157" timestamp="1289415730437" varLowerBound="-1.0" varUpperBound="-1.0" attrLowerBound="0.0" attrUpperBound="16.745098039215687" domLowerBound="0.0" domUpperBound="1.7976931348623157E308" />
      <trialInfo order="[[now2, nowCtxt2], [m1, now1, this1, this2], [m2, nowCtxt1, thisCtxt1, thisCtxt2]]" cost="362" timestamp="1289415731500" varLowerBound="43.8" varUpperBound="89.7" attrLowerBound="0.0" attrUpperBound="16.745098039215687" domLowerBound="0.0" domUpperBound="1.7976931348623157E308" />
      <trialInfo order="[[m1, nowCtxt1, thisCtxt1], m2, nowCtxt2, [now1, now2, this1], [this2, thisCtxt2]]" cost="197" timestamp="1289415732495" varLowerBound="-1.0" varUpperBound="-1.0" attrLowerBound="0.0" attrUpperBound="16.88235294117647" domLowerBound="0.0" domUpperBound="1.7976931348623157E308" />
      <trialInfo order="[now2, [now1, this1, thisCtxt1], [m1, m2], [nowCtxt1, nowCtxt2, this2, thisCtxt2]]" cost="12" timestamp="1289415733190" varLowerBound="-1.0" varUpperBound="-1.0" attrLowerBound="0.0" attrUpperBound="16.88235294117647" domLowerBound="0.0" domUpperBound="1.7976931348623157E308" />
      <trialInfo order="[m2, [now1, this1, thisCtxt1], this2, [m1, now2, nowCtxt1, nowCtxt2], thisCtxt2]" cost="184" timestamp="1289415734005" varLowerBound="0.0" varUpperBound="1.578723404255319" attrLowerBound="16.88235294117647" attrUpperBound="1.7976931348623157E308" domLowerBound="0.0" domUpperBound="1.7976931348623157E308" />
      <trialInfo order="[now2, [m1, this1, thisCtxt1], [m2, now1, nowCtxt1, this2, thisCtxt2], nowCtxt2]" cost="11" timestamp="1289415734735" varLowerBound="-1.0" varUpperBound="-1.0" attrLowerBound="0.0" attrUpperBound="16.88235294117647" domLowerBound="0.0" domUpperBound="1.7976931348623157E308" />
      <trialInfo order="[m2, [m1, now1, now2, nowCtxt1, nowCtxt2, this1, this2, thisCtxt1], thisCtxt2]" cost="1813" timestamp="1289415737402" varLowerBound="-1.0" varUpperBound="-1.0" attrLowerBound="16.88235294117647" attrUpperBound="1.7976931348623157E308" domLowerBound="0.0" domUpperBound="1.7976931348623157E308" />
      <trialInfo order="[[now1, this1], [m1, m2], [now2, nowCtxt1, nowCtxt2, thisCtxt1], this2, thisCtxt2]" cost="165" timestamp="1289415738183" varLowerBound="-1.0" varUpperBound="-1.0" attrLowerBound="-1.0" attrUpperBound="-1.0" domLowerBound="0.0" domUpperBound="1.7976931348623157E308" />
      <trialInfo order="[this2, [m1, m2, now1, now2, nowCtxt1, nowCtxt2, this1, thisCtxt1, thisCtxt2]]" cost="10000000" timestamp="1289415744320" varLowerBound="-1.0" varUpperBound="-1.0" attrLowerBound="18.058823529411764" attrUpperBound="1.7976931348623157E308" domLowerBound="0.0" domUpperBound="1.7976931348623157E308" />
      <trialInfo order="[[m1, now1, now2, this1], this2, [nowCtxt2, thisCtxt1, thisCtxt2], [m2, nowCtxt1]]" cost="167" timestamp="1289415745411" varLowerBound="-1.0" varUpperBound="-1.0" attrLowerBound="-1.0" attrUpperBound="-1.0" domLowerBound="0.0" domUpperBound="1.7976931348623157E308" />
      <trialInfo order="[[now1, nowCtxt1, this1, this2, thisCtxt2], [nowCtxt2, thisCtxt1], m1, [m2, now2]]" cost="309" timestamp="1289415746294" varLowerBound="-1.0" varUpperBound="-1.0" attrLowerBound="0.0" attrUpperBound="21.758823529411764" domLowerBound="0.0" domUpperBound="1.7976931348623157E308" />
      <trialInfo order="[[now1, this2], [nowCtxt1, this1], [m1, m2], [now2, nowCtxt2, thisCtxt1], thisCtxt2]" cost="944" timestamp="1289415747750" varLowerBound="-1.0" varUpperBound="-1.0" attrLowerBound="0.0" attrUpperBound="21.758823529411764" domLowerBound="0.0" domUpperBound="1.7976931348623157E308" />
      <trialInfo order="[[nowCtxt1, this1, thisCtxt1], m1, [now1, thisCtxt2], this2, m2, [now2, nowCtxt2]]" cost="6" timestamp="1289415748233" varLowerBound="0.0" varUpperBound="2.078723404255319" attrLowerBound="-1.0" attrUpperBound="-1.0" domLowerBound="0.0" domUpperBound="1.7976931348623157E308" />
      <trialInfo order="[[this1, this2], m1, [m2, thisCtxt2], [nowCtxt2, thisCtxt1], nowCtxt1, [now1, now2]]" cost="198" timestamp="1289415748929" varLowerBound="-1.0" varUpperBound="-1.0" attrLowerBound="0.0" attrUpperBound="21.758823529411764" domLowerBound="0.0" domUpperBound="1.7976931348623157E308" />
      <trialInfo order="[this2, [now2, nowCtxt1, thisCtxt1], now1, m1, thisCtxt2, m2, [nowCtxt2, this1]]" cost="210" timestamp="1289415749698" varLowerBound="-1.0" varUpperBound="-1.0" attrLowerBound="0.0" attrUpperBound="24.7" domLowerBound="0.0" domUpperBound="1.7976931348623157E308" />
      <trialInfo order="[[m1, m2], [nowCtxt1, thisCtxt1], [now1, now2, nowCtxt2, this2, thisCtxt2], this1]" cost="1144" timestamp="1289415751433" varLowerBound="-1.0" varUpperBound="-1.0" attrLowerBound="0.0" attrUpperBound="24.7" domLowerBound="0.0" domUpperBound="1.7976931348623157E308" />
    </episode>
  </episodeCollection>
</episodeCollections>

